scMethyAnno/__init__.py
scMethyAnno/data_preprocess.py
scMethyAnno/interpretation.py
scMethyAnno/loss.py
scMethyAnno/main.py
scMethyAnno/model.py
scMethyAnno/novel_discover.py
scMethyAnno/train_test.py
scmethyanno-1.1.1.dist-info/licenses/LICENSE.txt
scmethyanno-1.1.1.dist-info/METADATA
scmethyanno-1.1.1.dist-info/WHEEL
scmethyanno-1.1.1.dist-info/top_level.txt
scmethyanno-1.1.1.dist-info/RECORD
